Workbook
Name IQ_CH: 110000
Name IQ_CQ: 5000
Name IQ_CY: 10000
Name IQ_DAILY: 500000
Name IQ_FH: 100000
Name IQ_FQ: 500
Name IQ_FY: 1000
Name IQ_LTM: 2000
Name IQ_MONTH: 15000
Name IQ_NTM: 6000
Name IQ_WEEK: 50000
Name IQ_YTD: 3000

Sheet Start here
A1: Bloomberg price pull: 8 survivorship-ledger stocks
A2: Source of the list: docs/PRICE_REQUEST.md (MUST-HAVE rows, 95% of the missing headline dollars).
A4: ENGLISH
A5: 1. Open this file in Excel on a Bloomberg terminal (LBS library) and log in to Bloomberg first.
A6: 2. Go to the 'Setup' sheet. The YELLOW column D holds each Bloomberg identifier (my best guess). Leave it unless step 4 fails.
A7: 3. Each stock has its own sheet (X, ECOM, ...). Cell A2 holds a BDH formula; the data fills in by itself. If it doesn't, go to the Bloomberg tab in Excel and click 'Refresh Workbook'.
A8: 4. Back on 'Setup', column K says OK when the history ends within 5 days of the expected date. If it says 'Check identifier' or '0 rows': on the terminal, type the COMPANY NAME, press <GO>, pick the line marked 'Delisted' / 'Acquired', and paste its identifier (e.g. 1234567D US Equity) into column D.
A9: 5. When every row says OK: select all sheets' data, Copy, Paste Special > Values (so the numbers stay without Bloomberg), then Save.
A10: 6. Send the saved file to Claude. Claude turns each sheet into data/raw/manual_prices/<SYMBOL>.csv and fills in SOURCES.md.
A12: 中文
A13: 1. 在 LBS 图书馆的 Bloomberg 终端上用 Excel 打开本文件（先登录 Bloomberg）。
A14: 2. 打开 'Setup' 表。黄色的 D 列是每只股票的 Bloomberg 代码（我预先填好的猜测），一般不用改。
... A21: Legend: yellow fill = the only cells you may need to edit. Blue text = typed-in inputs (dates from docs/PRICE_REQUEST.md). Black = formulas.

Sheet Setup
A1: # | B1: Project symbol (sheet / CSV name) | C1: Company | D1: Bloomberg identifier (EDIT if needed) | E1: First date needed | F1: Last date needed | G1: Rows returned | H1: First date returned | I1: Last date returned | J1: Days short of expected end | K1: Check | L1: Notes
A2: 1 | B2: X | C2: United States Steel Corporation | D2: X US Equity | E2: 44396 | F2: 45826 | G2: =COUNT(X!A:A) -> 984 | H2: =IF(G2>0,MIN(X!A:A),"") -> 44396 | I2: =IF(G2>0,MAX(X!A:A),"") -> 45825 | J2: =IF(G2>0,F2-I2,"") -> 1 | K2: =IF(G2=0,"0 rows: not pulled yet",IF(ABS(J2)<=5,"OK","Check identifier")) -> OK | L2: Acquired by Nippon Steel for $55 cash, closed 18 Jun 2025.
A3: 2 | B3: ECOM | C3: ChannelAdvisor Corporation | D3: ECOM US Equity | E3: 44396 | F3: 44880 | G3: =COUNT(ECOM!A:A) -> 336 | H3: =IF(G3>0,MIN(ECOM!A:A),"") -> 44396 | I3: =IF(G3>0,MAX(ECOM!A:A),"") -> 44879 | J3: =IF(G3>0,F3-I3,"") -> 1 | K3: =IF(G3=0,"0 rows: not pulled yet",IF(ABS(J3)<=5,"OK","Check identifier")) -> OK | L3: Acquired by CommerceHub for $23.10 cash, Nov 2022.
A4: 3 | B4: ATVI | C4: Activision Blizzard, Inc. | D4: ATVI US Equity | E4: 43566 | F4: 45212 | G4: =COUNT(ATVI!A:A) -> 1135 | H4: =IF(G4>0,MIN(ATVI!A:A),"") -> 43566 | I4: =IF(G4>0,MAX(ATVI!A:A),"") -> 45211 | J4: =IF(G4>0,F4-I4,"") -> 1 | K4: =IF(G4=0,"0 rows: not pulled yet",IF(ABS(J4)<=5,"OK","Check identifier")) -> OK | L4: Acquired by Microsoft for $95 cash, closed 13 Oct 2023.
A5: 4 | B5: SSBK | C5: Southern States Bancshares, Inc. | D5: SSBK US Equity | E5: 44440 | F5: 45839 | G5: =COUNT(SSBK!A:A) -> 952 | H5: =IF(G5>0,MIN(SSBK!A:A),"") -> 44440 | I5: =IF(G5>0,MAX(SSBK!A:A),"") -> 45838 | J5: =IF(G5>0,F5-I5,"") -> 1 | K5: =IF(G5=0,"0 rows: not pulled yet",IF(ABS(J5)<=5,"OK","Check identifier")) -> OK | L5: Merged into FB Financial (0.80 FBK per share), 1 Jul 2025.
A6: 5 | B6: PARA | C6: Paramount Global - Class B | D6: 2677689D US Equity | E6: 45208 | F6: 45876 | G6: =COUNT(PARA!A:A) -> 458 | H6: =IF(G6>0,MIN(PARA!A:A),"") -> 45208 | I6: =IF(G6>0,MAX(PARA!A:A),"") -> 45875 | J6: =IF(G6>0,F6-I6,"") -> 1 | K6: =IF(G6=0,"0 rows: not pulled yet",IF(ABS(J6)<=5,"OK","Check identifier")) -> OK | L6: Skydance merger closed 7 Aug 2025. The ticker may now point to the NEW company: pick the old Paramount Global Class B line.
A7: 6 | B7: WBA | C7: Walgreens Boots Alliance, Inc. | D7: WBA US Equity | E7: 42507 | F7: 45897 | G7: =COUNT(WBA!A:A) -> 2334 | H7: =IF(G7>0,MIN(WBA!A:A),"") -> 42507 | I7: =IF(G7>0,MAX(WBA!A:A),"") -> 45896 | J7: =IF(G7>0,F7-I7,"") -> 1 | K7: =IF(G7=0,"0 rows: not pulled yet",IF(ABS(J7)<=5,"OK","Check identifier")) -> OK | L7: Taken private by Sycamore Partners, Aug 2025.
A8: 7 | B8: GOGL | C8: Golden Ocean Group Limited | D8: 2663476D US Equity | E8: 45362 | F8: 45889 | G8: =COUNT(GOGL!A:A) -> 362 | H8: =IF(G8>0,MIN(GOGL!A:A),"") -> 45362 | I8: =IF(G8>0,MAX(GOGL!A:A),"") -> 45888 | J8: =IF(G8>0,F8-I8,"") -> 1 | K8: =IF(G8=0,"0 rows: not pulled yet",IF(ABS(J8)<=5,"OK","Check identifier")) -> OK | L8: Merged into CMB.TECH, Aug 2025. Use the US (NASDAQ) line, not Oslo.
A9: 8 | B9: TOELY | C9: Tokyo Electron Ltd ADR | D9: TOELY US Equity | E9: 46218 | F9: 46265 | G9: =COUNT(TOELY!A:A) -> 34 | H9: =IF(G9>0,MIN(TOELY!A:A),"") -> 46218 | I9: =IF(G9>0,MAX(TOELY!A:A),"") -> 46265 | J9: =IF(G9>0,F9-I9,"") -> 0 | K9: =IF(G9=0,"0 rows: not pulled yet",IF(ABS(J9)<=5,"OK","Check identifier")) -> OK | L9: Still trades (US OTC ADR). History should run to 31 Aug 2026.

Sheet X
A1: date | B1: close | C1: total_return_index
A2: {=_xll.BDH(Setup!$D$2,"PX_LAST,TOT_RETURN_INDEX_GROSS_DVDS",Setup!$E$2,Setup!$F$2,"Days=T","Fill=B","Sort=A")} -> 44396 | B2: 21.5 | C2: 21.5
A3: 44397 | B3: 22.06 | C3: 22.06
A4: 44398 | B4: 23.06 | C4: 23.06
A5: 44399 | B5: 23.04 | C5: 23.04
A6: 44400 | B6: 23.13 | C6: 23.13
A7: 44403 | B7: 24.15 | C7: 24.15
A8: 44404 | B8: 23.84 | C8: 23.84
A9: 44405 | B9: 24.55 | C9: 24.55
A10: 44406 | B10: 25.47 | C10: 25.47
A11: 44407 | B11: 26.48 | C11: 26.48
A12: 44410 | B12: 25.07 | C12: 25.07
A13: 44411 | B13: 25.87 | C13: 25.87
A14: 44412 | B14: 25.24 | C14: 25.24
... A985: 45825 | B985: 54.84 | C985: 56.277

Sheet ECOM
A1: date | B1: close | C1: total_return_index
A2: {=_xll.BDH(Setup!$D$3,"PX_LAST,TOT_RETURN_INDEX_GROSS_DVDS",Setup!$E$3,Setup!$F$3,"Days=T","Fill=B","Sort=A")} -> 44396 | B2: 22.7 | C2: 22.7
A3: 44397 | B3: 22.98 | C3: 22.98
A4: 44398 | B4: 22.98 | C4: 22.98
A5: 44399 | B5: 22.63 | C5: 22.63
A6: 44400 | B6: 22.94 | C6: 22.94
A7: 44403 | B7: 23.19 | C7: 23.19
A8: 44404 | B8: 22.99 | C8: 22.99
A9: 44405 | B9: 23.1 | C9: 23.1
A10: 44406 | B10: 23.48 | C10: 23.48
A11: 44407 | B11: 23.29 | C11: 23.29
A12: 44410 | B12: 23.17 | C12: 23.17
A13: 44411 | B13: 23.29 | C13: 23.29
A14: 44412 | B14: 22.69 | C14: 22.69
... A337: 44879 | B337: 23.09 | C337: 23.09

Sheet ATVI
A1: date | B1: close | C1: total_return_index
A2: {=_xll.BDH(Setup!$D$4,"PX_LAST,TOT_RETURN_INDEX_GROSS_DVDS",Setup!$E$4,Setup!$F$4,"Days=T","Fill=B","Sort=A")} -> 43566 | B2: 47.17 | C2: 47.17
A3: 43567 | B3: 47.28 | C3: 47.28
A4: 43570 | B4: 45.75 | C4: 45.75
A5: 43571 | B5: 45.06 | C5: 45.06
A6: 43572 | B6: 44.98 | C6: 44.98
A7: 43573 | B7: 45.31 | C7: 45.31
A8: 43577 | B8: 45.34 | C8: 45.34
A9: 43578 | B9: 46.51 | C9: 46.51
A10: 43579 | B10: 46.75 | C10: 46.75
A11: 43580 | B11: 47.41 | C11: 47.41
A12: 43581 | B12: 48.15 | C12: 48.15
A13: 43584 | B13: 48.4 | C13: 48.4
A14: 43585 | B14: 48.21 | C14: 48.21
... A1136: 45211 | B1136: 94.42 | C1136: 97.096

Sheet SSBK
A1: date | B1: close | C1: total_return_index
A2: {=_xll.BDH(Setup!$D$5,"PX_LAST,TOT_RETURN_INDEX_GROSS_DVDS",Setup!$E$5,Setup!$F$5,"Days=T","Fill=B","Sort=A")} -> 44440 | B2: 19.41 | C2: 19.41
A3: 44441 | B3: 19.35 | C3: 19.35
A4: 44442 | B4: 19.69 | C4: 19.69
A5: 44446 | B5: 19.76 | C5: 19.76
A6: 44447 | B6: 19.75 | C6: 19.75
A7: 44448 | B7: 19.7248 | C7: 19.7248
A8: 44449 | B8: 19.7 | C8: 19.7
A9: 44452 | B9: 19.8 | C9: 19.8
A10: 44453 | B10: 19.8 | C10: 19.8
A11: 44454 | B11: 19.7 | C11: 19.7
A12: 44455 | B12: 19.7 | C12: 19.7
A13: 44456 | B13: 19.06 | C13: 19.06
A14: 44459 | B14: 19.465 | C14: 19.465
... A953: 45838 | B953: 36.37 | C953: 38.3358

Sheet PARA
A1: date | B1: close | C1: total_return_index
A2: {=_xll.BDH(Setup!$D$6,"PX_LAST,TOT_RETURN_INDEX_GROSS_DVDS",Setup!$E$6,Setup!$F$6,"Days=T","Fill=B","Sort=A")} -> 45208 | B2: 11.96 | C2: 11.96
A3: 45209 | B3: 12.43 | C3: 12.43
A4: 45210 | B4: 12.14 | C4: 12.14
A5: 45211 | B5: 11.73 | C5: 11.73
A6: 45212 | B6: 11.9 | C6: 11.9
A7: 45215 | B7: 12.26 | C7: 12.26
A8: 45216 | B8: 12.46 | C8: 12.46
A9: 45217 | B9: 12.19 | C9: 12.19
A10: 45218 | B10: 11.78 | C10: 11.78
A11: 45219 | B11: 11.5 | C11: 11.5
A12: 45222 | B12: 11.19 | C12: 11.19
A13: 45223 | B13: 11.15 | C13: 11.15
A14: 45224 | B14: 10.94 | C14: 10.94
... A459: 45875 | B459: 11.04 | C459: 11.3791

Sheet WBA
A1: date | B1: close | C1: total_return_index
A2: {=_xll.BDH(Setup!$D$7,"PX_LAST,TOT_RETURN_INDEX_GROSS_DVDS",Setup!$E$7,Setup!$F$7,"Days=T","Fill=B","Sort=A")} -> 42507 | B2: 76.48 | C2: 76.48
A3: 42508 | B3: 76.54 | C3: 76.54
A4: 42509 | B4: 76.21 | C4: 76.21
A5: 42510 | B5: 77.22 | C5: 77.22
A6: 42513 | B6: 76.53 | C6: 76.53
A7: 42514 | B7: 77.15 | C7: 77.15
A8: 42515 | B8: 77.63 | C8: 77.63
A9: 42516 | B9: 76.78 | C9: 76.78
A10: 42517 | B10: 77 | C10: 77
A11: 42521 | B11: 77.4 | C11: 77.4
A12: 42522 | B12: 78.1 | C12: 78.1
A13: 42523 | B13: 79.1 | C13: 79.1
A14: 42524 | B14: 78.68 | C14: 78.68
... A2335: 45896 | B2335: 11.98 | C2335: 17.1239

Sheet GOGL
A1: date | B1: close | C1: total_return_index
A2: {=_xll.BDH(Setup!$D$8,"PX_LAST,TOT_RETURN_INDEX_GROSS_DVDS",Setup!$E$8,Setup!$F$8,"Days=T","Fill=B","Sort=A")} -> 45362 | B2: 13.44 | C2: 13.44
A3: 45363 | B3: 13.44 | C3: 13.74
A4: 45364 | B4: 13.16 | C4: 13.4538
A5: 45365 | B5: 12.89 | C5: 13.1777
A6: 45366 | B6: 12.8 | C6: 13.0857
A7: 45369 | B7: 12.95 | C7: 13.2391
A8: 45370 | B8: 12.81 | C8: 13.0959
A9: 45371 | B9: 12.59 | C9: 12.871
A10: 45372 | B10: 12.88 | C10: 13.1675
A11: 45373 | B11: 12.85 | C11: 13.1368
A12: 45376 | B12: 12.66 | C12: 12.9426
A13: 45377 | B13: 12.54 | C13: 12.8199
A14: 45378 | B14: 12.78 | C14: 13.0653
... A363: 45888 | B363: 7.98 | C363: 9.0633

Sheet TOELY
A1: date | B1: close | C1: total_return_index
A2: {=_xll.BDH(Setup!$D$9,"PX_LAST,TOT_RETURN_INDEX_GROSS_DVDS",Setup!$E$9,Setup!$F$9,"Days=T","Fill=B","Sort=A")} -> 46218 | B2: 218.8 | C2: 218.8
A3: 46219 | B3: 211.53 | C3: 211.53
A4: 46220 | B4: 202.94 | C4: 202.94
A5: 46223 | B5: 201.81 | C5: 201.81
A6: 46224 | B6: 209.15 | C6: 209.15
A7: 46225 | B7: 204.5275 | C7: 204.5275
A8: 46226 | B8: 199.58 | C8: 199.58
A9: 46227 | B9: 188.09 | C9: 188.09
A10: 46230 | B10: 184.5 | C10: 184.5
A11: 46231 | B11: 165.9 | C11: 165.9
A12: 46232 | B12: 150 | C12: 150
A13: 46233 | B13: 173.5 | C13: 173.5
A14: 46234 | B14: 167.37 | C14: 167.37
... A35: 46265 | B35: 175.33 | C35: 175.33
